{
  "error": null,
  "data": {
    "results": [
      {
        "id": 13,
        "created_by": {
          "id": 5,
          "username": "test_user_username",
          "real_name": null
        },
        "title": "test",
        "category": "Free",
        "views": 0,
        "create_time": "2021-07-30T07:07:46.762415Z",
        "last_update_time": "2021-07-30T07:07:46.762442Z"
      },
      {
        "id": 11,
        "created_by": {
          "id": 5,
          "username": "test_user_username",
          "real_name": null
        },
        "title": "test",
        "category": "Free",
        "views": 0,
        "create_time": "2021-07-30T07:07:46.749111Z",
        "last_update_time": "2021-07-30T07:07:46.749138Z"
      },
      {
        "id": 9,
        "created_by": {
          "id": 5,
          "username": "test_user_username",
          "real_name": null
        },
        "title": "test",
        "category": "Free",
        "views": 0,
        "create_time": "2021-07-30T07:07:46.733925Z",
        "last_update_time": "2021-07-30T07:07:46.733948Z"
      },
      {
        "id": 7,
        "created_by": {
          "id": 5,
          "username": "test_user_username",
          "real_name": null
        },
        "title": "test",
        "category": "Free",
        "views": 0,
        "create_time": "2021-07-30T07:07:46.721200Z",
        "last_update_time": "2021-07-30T07:07:46.721224Z"
      }
    ],
    "total": 4
  }
}
